core_utils/__init__.py
core_utils/user_collection.py
dummy/__init__.py
dummy/say_hello.py
utils_rbiswasfc-0.0.1.dist-info/LICENSE
utils_rbiswasfc-0.0.1.dist-info/METADATA
utils_rbiswasfc-0.0.1.dist-info/WHEEL
utils_rbiswasfc-0.0.1.dist-info/top_level.txt
utils_rbiswasfc-0.0.1.dist-info/RECORD
