Metadata-Version: 2.1
Name: utils-rbiswasfc
Version: 0.0.1
Summary: A collection of utility functions
Home-page: https://github.com/rbiswasfc/utils
Author: Raja Biswas
Author-email: rajabiswas92@outlook.com
License: UNKNOWN
Project-URL: Bug Tracker, https://github.com/rbiswasfc/utils/issues
Platform: UNKNOWN
Classifier: Programming Language :: Python :: 3
Classifier: License :: OSI Approved :: GNU General Public License v3 (GPLv3)
Classifier: Operating System :: OS Independent
Requires-Python: >=3.6
License-File: LICENSE
